fishknn/__init__.py
fishknn/what_fish_name.py
fishknn-0.1.4.dist-info/METADATA
fishknn-0.1.4.dist-info/WHEEL
fishknn-0.1.4.dist-info/entry_points.txt
fishknn-0.1.4.dist-info/top_level.txt
fishknn-0.1.4.dist-info/RECORD
