Metadata-Version: 2.1
Name: fishknn
Version: 0.1.4
Summary: Fish predictor with KNN
Author-email: Kimwonjoon <kimpass189@gmail.com>
License: MIT
Project-URL: Homepage, https://github.com/Kimwonjoon/fishknn
Project-URL: Issues, https://github.com/Kimwonjoon/fishknn/issues
Requires-Python: >=3.11
Requires-Dist: pandas>=2.2.2
Requires-Dist: pyarrow>=17.0.0
Requires-Dist: scikit-learn>=1.5.1
Requires-Dist: matplotlib>=3.9.2
